qrotor/__init__.py
qrotor/_version.py
qrotor/constants.py
qrotor/plot.py
qrotor/potential.py
qrotor/rotation.py
qrotor/solve.py
qrotor/system.py
qrotor/systems.py
qrotor-4.6.0.dist-info/licenses/LICENSE
qrotor-4.6.0.dist-info/METADATA
qrotor-4.6.0.dist-info/WHEEL
qrotor-4.6.0.dist-info/top_level.txt
qrotor-4.6.0.dist-info/RECORD
