Metadata-Version: 2.4
Name: qrotor
Version: 4.6.0
Summary: QRotor
Author: Pablo Gila-Herranz
Author-email: pgila001@ikasle.ehu.eus
License: AGPL-3.0
Keywords: QRotor,Molecular rotations,Quantum rotations,Quantum,Molecular,Rotations,Neutrons,Research,Ab-initio,DFT,Density Functional Theory,Quantum ESPRESSO,Phonons,Electronic structure
Classifier: Development Status :: 5 - Production/Stable
Classifier: Natural Language :: English
Classifier: Intended Audience :: Science/Research
Classifier: Programming Language :: Python :: 3
Classifier: Operating System :: POSIX :: Linux
Classifier: Operating System :: Microsoft :: Windows
Classifier: Operating System :: Other OS
Requires-Python: >=3
License-File: LICENSE
Requires-Dist: scipy
Requires-Dist: pandas
Requires-Dist: numpy
Requires-Dist: matplotlib
Requires-Dist: aton
Requires-Dist: periodictable
Dynamic: author
Dynamic: author-email
Dynamic: classifier
Dynamic: description
Dynamic: description-content-type
Dynamic: keywords
Dynamic: license
Dynamic: license-file
Dynamic: requires-dist
Dynamic: requires-python
Dynamic: summary
